MOBPY/__init__.py
MOBPY/config.py
MOBPY/exceptions.py
MOBPY/logging_utils.py
MOBPY/binning/__init__.py
MOBPY/binning/mob.py
MOBPY/binning/__pycache__/__init__.py
MOBPY/core/__init__.py
MOBPY/core/constraints.py
MOBPY/core/merge.py
MOBPY/core/pava.py
MOBPY/core/utils.py
MOBPY/plot/__init__.py
MOBPY/plot/csd_gcm.py
MOBPY/plot/mob_plot.py
mobpy-2.1.0.dist-info/licenses/LICENSE
mobpy-2.1.0.dist-info/METADATA
mobpy-2.1.0.dist-info/WHEEL
mobpy-2.1.0.dist-info/top_level.txt
mobpy-2.1.0.dist-info/RECORD
