Metadata-Version: 2.4
Name: MOBPY
Version: 2.1.0
Summary: Monotone optimal binning (MOB) via PAVA with constraints, plus plotting utilities.
Author-email: "Ta-Hung (Denny) Chen" <denny20700@gmail.com>
Maintainer-email: "Ta-Hung (Denny) Chen" <denny20700@gmail.com>
License: MIT
Project-URL: Homepage, https://github.com/ChenTaHung/Monotonic-Optimal-Binning
Project-URL: Repository, https://github.com/ChenTaHung/Monotonic-Optimal-Binning
Project-URL: Issues, https://github.com/ChenTaHung/Monotonic-Optimal-Binning/issues
Project-URL: Documentation, https://github.com/ChenTaHung/Monotonic-Optimal-Binning/tree/main/docs
Project-URL: Release Notes, https://github.com/ChenTaHung/Monotonic-Optimal-Binning/releases
Keywords: binning,woe,iv,pava,isotonic,credit-risk,monotonic,scorecard,feature-engineering
Classifier: Development Status :: 5 - Production/Stable
Classifier: Intended Audience :: Science/Research
Classifier: Intended Audience :: Developers
Classifier: Intended Audience :: Financial and Insurance Industry
Classifier: Programming Language :: Python
Classifier: Programming Language :: Python :: 3 :: Only
Classifier: Programming Language :: Python :: 3.9
Classifier: Programming Language :: Python :: 3.10
Classifier: Programming Language :: Python :: 3.11
Classifier: Programming Language :: Python :: 3.12
Classifier: Topic :: Scientific/Engineering :: Information Analysis
Classifier: Topic :: Scientific/Engineering :: Mathematics
Classifier: Topic :: Software Development :: Libraries :: Python Modules
Classifier: Operating System :: OS Independent
Requires-Python: >=3.9
License-File: LICENSE
Requires-Dist: numpy>=1.20.0
Requires-Dist: pandas>=1.3.0
Requires-Dist: scipy>=1.7.0
Requires-Dist: matplotlib>=3.3.0
Provides-Extra: test
Requires-Dist: pytest>=8.0; extra == "test"
Requires-Dist: pytest-mock>=3.15; extra == "test"
Requires-Dist: hypothesis>=6.100; extra == "test"
Requires-Dist: pytest-cov>=4.0; extra == "test"
Provides-Extra: dev
Requires-Dist: pytest>=8.0; extra == "dev"
Requires-Dist: hypothesis>=6.100; extra == "dev"
Requires-Dist: pytest-cov>=4.0; extra == "dev"
Requires-Dist: black>=23.0; extra == "dev"
Requires-Dist: isort>=5.12; extra == "dev"
Requires-Dist: flake8>=6.0; extra == "dev"
Requires-Dist: mypy>=1.0; extra == "dev"
Requires-Dist: pre-commit>=3.0; extra == "dev"
Provides-Extra: docs
Requires-Dist: sphinx>=6.0; extra == "docs"
Requires-Dist: sphinx-rtd-theme>=1.3; extra == "docs"
Requires-Dist: nbsphinx>=0.9; extra == "docs"
Dynamic: license-file
